[
    {
        "num": "2811209702774",
        "id": "076",
        "acc": 99.33151740294237
    },
    {
        "name": "2",
        "percentage_probability": 99.8157799243927,
        "box_points": [
            45,
            64,
            51,
            84
        ],
        "alert": "false"
    },
    {
        "name": "8",
        "percentage_probability": 99.90981221199036,
        "box_points": [
            52,
            65,
            56,
            83
        ],
        "alert": "false"
    },
    {
        "name": "1",
        "percentage_probability": 99.86793398857117,
        "box_points": [
            59,
            64,
            62,
            84
        ],
        "alert": "false"
    },
    {
        "name": "1",
        "percentage_probability": 99.69184994697571,
        "box_points": [
            65,
            64,
            68,
            84
        ],
        "alert": "false"
    },
    {
        "name": "2",
        "percentage_probability": 99.05102252960205,
        "box_points": [
            71,
            64,
            76,
            83
        ],
        "alert": "false"
    },
    {
        "name": "0",
        "percentage_probability": 99.36497211456299,
        "box_points": [
            77,
            63,
            82,
            82
        ],
        "alert": "false"
    },
    {
        "name": "9",
        "percentage_probability": 95.94772458076477,
        "box_points": [
            84,
            63,
            89,
            82
        ],
        "alert": "true"
    },
    {
        "name": "7",
        "percentage_probability": 99.9366819858551,
        "box_points": [
            90,
            61,
            94,
            82
        ],
        "alert": "false"
    },
    {
        "name": "0",
        "percentage_probability": 99.79034066200256,
        "box_points": [
            97,
            62,
            102,
            81
        ],
        "alert": "false"
    },
    {
        "name": "2",
        "percentage_probability": 99.823659658432,
        "box_points": [
            104,
            61,
            110,
            82
        ],
        "alert": "false"
    },
    {
        "name": "7",
        "percentage_probability": 99.37598705291748,
        "box_points": [
            122,
            58,
            128,
            81
        ],
        "alert": "false"
    },
    {
        "name": "7",
        "percentage_probability": 99.26743507385254,
        "box_points": [
            129,
            58,
            134,
            81
        ],
        "alert": "false"
    },
    {
        "name": "4",
        "percentage_probability": 99.4665265083313,
        "box_points": [
            135,
            58,
            141,
            81
        ],
        "alert": "false"
    }
]