[
    {
        "name": "2",
        "percentage_probability": 99.77771639823914,
        "box_points": [
            60,
            60,
            66,
            79
        ],
        "alert": "false"
    },
    {
        "name": "8",
        "percentage_probability": 99.89266395568848,
        "box_points": [
            68,
            60,
            73,
            78
        ],
        "alert": "false"
    },
    {
        "name": "1",
        "percentage_probability": 99.46767687797546,
        "box_points": [
            75,
            60,
            79,
            79
        ],
        "alert": "false"
    },
    {
        "name": "1",
        "percentage_probability": 99.60187673568726,
        "box_points": [
            81,
            60,
            84,
            79
        ],
        "alert": "false"
    },
    {
        "name": "2",
        "percentage_probability": 99.77720379829407,
        "box_points": [
            86,
            60,
            91,
            78
        ],
        "alert": "false"
    },
    {
        "name": "8",
        "percentage_probability": 99.38094019889832,
        "box_points": [
            93,
            60,
            98,
            78
        ],
        "alert": "false"
    },
    {
        "name": "9",
        "percentage_probability": 98.58499765396118,
        "box_points": [
            99,
            60,
            104,
            79
        ],
        "alert": "true"
    },
    {
        "name": "7",
        "percentage_probability": 99.76330399513245,
        "box_points": [
            106,
            60,
            110,
            79
        ],
        "alert": "false"
    },
    {
        "name": "0",
        "percentage_probability": 99.93801712989807,
        "box_points": [
            112,
            60,
            116,
            79
        ],
        "alert": "false"
    },
    {
        "name": "2",
        "percentage_probability": 99.93669986724854,
        "box_points": [
            119,
            60,
            124,
            79
        ],
        "alert": "false"
    },
    {
        "name": "7",
        "percentage_probability": 99.89850521087646,
        "box_points": [
            136,
            60,
            142,
            80
        ],
        "alert": "false"
    },
    {
        "name": "7",
        "percentage_probability": 99.90776777267456,
        "box_points": [
            143,
            60,
            148,
            80
        ],
        "alert": "false"
    },
    {
        "name": "5",
        "percentage_probability": 99.39510226249695,
        "box_points": [
            150,
            61,
            155,
            80
        ],
        "alert": "false"
    },
    {
        "media": 99.64019014285161
    },
    {
        "imagem": "079"
    },
    {
        "numero": "2811289702775"
    }
]