[
    {
        "name": "2",
        "percentage_probability": 99.77073669433594,
        "box_points": [
            56,
            60,
            62,
            79
        ],
        "alert": "false"
    },
    {
        "name": "8",
        "percentage_probability": 99.93937015533447,
        "box_points": [
            63,
            60,
            68,
            79
        ],
        "alert": "false"
    },
    {
        "name": "1",
        "percentage_probability": 99.80373978614807,
        "box_points": [
            70,
            61,
            73,
            80
        ],
        "alert": "false"
    },
    {
        "name": "1",
        "percentage_probability": 99.58412647247314,
        "box_points": [
            75,
            60,
            79,
            80
        ],
        "alert": "false"
    },
    {
        "name": "2",
        "percentage_probability": 99.50032830238342,
        "box_points": [
            81,
            60,
            85,
            80
        ],
        "alert": "false"
    },
    {
        "name": "0",
        "percentage_probability": 98.84163737297058,
        "box_points": [
            87,
            61,
            92,
            79
        ],
        "alert": "true"
    },
    {
        "name": "8",
        "percentage_probability": 98.35416078567505,
        "box_points": [
            94,
            61,
            99,
            80
        ],
        "alert": "true"
    },
    {
        "name": "7",
        "percentage_probability": 99.8380959033966,
        "box_points": [
            99,
            60,
            104,
            80
        ],
        "alert": "false"
    },
    {
        "name": "0",
        "percentage_probability": 99.83270168304443,
        "box_points": [
            105,
            62,
            110,
            79
        ],
        "alert": "false"
    },
    {
        "name": "2",
        "percentage_probability": 99.89814758300781,
        "box_points": [
            112,
            61,
            117,
            81
        ],
        "alert": "false"
    },
    {
        "name": "7",
        "percentage_probability": 99.93348717689514,
        "box_points": [
            129,
            61,
            135,
            82
        ],
        "alert": "false"
    },
    {
        "name": "4",
        "percentage_probability": 99.56132173538208,
        "box_points": [
            136,
            63,
            141,
            81
        ],
        "alert": "false"
    },
    {
        "name": "7",
        "percentage_probability": 99.69910979270935,
        "box_points": [
            142,
            62,
            148,
            81
        ],
        "alert": "false"
    },
    {
        "media": 99.58130488028893
    },
    {
        "imagem": "065"
    },
    {
        "numero": "2811208702747"
    }
]