[
    {
        "num": "2811209702746",
        "id": "083",
        "acc": 99.2817617379702
    },
    {
        "name": "2",
        "percentage_probability": 99.93829131126404,
        "box_points": [
            59,
            58,
            65,
            77
        ],
        "alert": "false"
    },
    {
        "name": "8",
        "percentage_probability": 99.91554617881775,
        "box_points": [
            66,
            59,
            71,
            76
        ],
        "alert": "false"
    },
    {
        "name": "1",
        "percentage_probability": 99.84473586082458,
        "box_points": [
            73,
            59,
            76,
            78
        ],
        "alert": "false"
    },
    {
        "name": "1",
        "percentage_probability": 99.73286986351013,
        "box_points": [
            79,
            59,
            82,
            78
        ],
        "alert": "false"
    },
    {
        "name": "2",
        "percentage_probability": 99.52952861785889,
        "box_points": [
            85,
            58,
            89,
            78
        ],
        "alert": "false"
    },
    {
        "name": "0",
        "percentage_probability": 97.41414785385132,
        "box_points": [
            91,
            59,
            96,
            78
        ],
        "alert": "true"
    },
    {
        "name": "9",
        "percentage_probability": 97.8358805179596,
        "box_points": [
            97,
            60,
            102,
            78
        ],
        "alert": "true"
    },
    {
        "name": "7",
        "percentage_probability": 99.86401796340942,
        "box_points": [
            104,
            59,
            108,
            78
        ],
        "alert": "false"
    },
    {
        "name": "0",
        "percentage_probability": 99.5929479598999,
        "box_points": [
            110,
            61,
            115,
            78
        ],
        "alert": "false"
    },
    {
        "name": "2",
        "percentage_probability": 99.5667576789856,
        "box_points": [
            117,
            61,
            123,
            80
        ],
        "alert": "false"
    },
    {
        "name": "7",
        "percentage_probability": 99.90383982658386,
        "box_points": [
            134,
            61,
            140,
            81
        ],
        "alert": "false"
    },
    {
        "name": "4",
        "percentage_probability": 99.7635006904602,
        "box_points": [
            142,
            61,
            147,
            81
        ],
        "alert": "false"
    },
    {
        "name": "6",
        "percentage_probability": 97.76083827018738,
        "box_points": [
            149,
            62,
            155,
            80
        ],
        "alert": "true"
    }
]