[
    {
        "num": "2811209702797",
        "id": "043",
        "acc": 99.49787900998042,
        "alert": "false"
    },
    {
        "name": "2",
        "percentage_probability": 99.91076588630676,
        "box_points": [
            58,
            70,
            64,
            91
        ],
        "alert": "false"
    },
    {
        "name": "8",
        "percentage_probability": 99.86053705215454,
        "box_points": [
            66,
            71,
            71,
            90
        ],
        "alert": "false"
    },
    {
        "name": "1",
        "percentage_probability": 99.8318612575531,
        "box_points": [
            73,
            71,
            76,
            91
        ],
        "alert": "false"
    },
    {
        "name": "1",
        "percentage_probability": 99.80257153511047,
        "box_points": [
            79,
            70,
            83,
            94
        ],
        "alert": "false"
    },
    {
        "name": "2",
        "percentage_probability": 99.62913990020752,
        "box_points": [
            85,
            70,
            90,
            94
        ],
        "alert": "false"
    },
    {
        "name": "0",
        "percentage_probability": 99.10486936569214,
        "box_points": [
            92,
            72,
            98,
            92
        ],
        "alert": "false"
    },
    {
        "name": "9",
        "percentage_probability": 96.22923731803894,
        "box_points": [
            99,
            73,
            104,
            93
        ],
        "alert": "true"
    },
    {
        "name": "7",
        "percentage_probability": 99.91605281829834,
        "box_points": [
            106,
            71,
            111,
            95
        ],
        "alert": "false"
    },
    {
        "name": "0",
        "percentage_probability": 99.80078935623169,
        "box_points": [
            112,
            74,
            117,
            95
        ],
        "alert": "false"
    },
    {
        "name": "2",
        "percentage_probability": 99.86733198165894,
        "box_points": [
            120,
            74,
            125,
            96
        ],
        "alert": "false"
    },
    {
        "name": "7",
        "percentage_probability": 99.89556074142456,
        "box_points": [
            139,
            74,
            144,
            97
        ],
        "alert": "false"
    },
    {
        "name": "9",
        "percentage_probability": 99.88439083099365,
        "box_points": [
            146,
            75,
            151,
            97
        ],
        "alert": "false"
    },
    {
        "name": "7",
        "percentage_probability": 99.73931908607483,
        "box_points": [
            153,
            74,
            159,
            98
        ],
        "alert": "false"
    }
]