[
    {
        "num": "2810879302750",
        "id": "037",
        "acc": 99.60763775385342,
        "alert": "false"
    },
    {
        "name": "2",
        "percentage_probability": 99.71688985824585,
        "box_points": [
            52,
            79,
            60,
            106
        ],
        "alert": "false"
    },
    {
        "name": "8",
        "percentage_probability": 99.85561966896057,
        "box_points": [
            62,
            79,
            69,
            106
        ],
        "alert": "false"
    },
    {
        "name": "1",
        "percentage_probability": 99.78355169296265,
        "box_points": [
            71,
            79,
            76,
            106
        ],
        "alert": "false"
    },
    {
        "name": "0",
        "percentage_probability": 99.7327446937561,
        "box_points": [
            79,
            79,
            85,
            106
        ],
        "alert": "false"
    },
    {
        "name": "8",
        "percentage_probability": 99.71526861190796,
        "box_points": [
            88,
            80,
            94,
            105
        ],
        "alert": "false"
    },
    {
        "name": "7",
        "percentage_probability": 99.65388774871826,
        "box_points": [
            96,
            76,
            102,
            108
        ],
        "alert": "false"
    },
    {
        "name": "9",
        "percentage_probability": 99.80522394180298,
        "box_points": [
            104,
            78,
            111,
            106
        ],
        "alert": "false"
    },
    {
        "name": "3",
        "percentage_probability": 99.79498386383057,
        "box_points": [
            113,
            78,
            119,
            106
        ],
        "alert": "false"
    },
    {
        "name": "0",
        "percentage_probability": 99.79414343833923,
        "box_points": [
            121,
            79,
            128,
            105
        ],
        "alert": "false"
    },
    {
        "name": "2",
        "percentage_probability": 99.76097345352173,
        "box_points": [
            131,
            79,
            137,
            106
        ],
        "alert": "false"
    },
    {
        "name": "7",
        "percentage_probability": 98.98731112480164,
        "box_points": [
            154,
            76,
            162,
            106
        ],
        "alert": "true"
    },
    {
        "name": "5",
        "percentage_probability": 98.81860017776489,
        "box_points": [
            163,
            78,
            170,
            105
        ],
        "alert": "true"
    },
    {
        "name": "0",
        "percentage_probability": 99.48009252548218,
        "box_points": [
            173,
            79,
            180,
            106
        ],
        "alert": "false"
    }
]